LICENSE
MANIFEST.in
README.md
setup.py
bdea/__init__.py
bdea/client.py
bdea/django_validators.py
block_disposable_email.egg-info/PKG-INFO
block_disposable_email.egg-info/SOURCES.txt
block_disposable_email.egg-info/dependency_links.txt
block_disposable_email.egg-info/top_level.txt