Metadata-Version: 1.1
Name: block-disposable-email
Version: 2.0.0
Summary: Python client for block-disposable-email.com
Home-page: http://github.com/max-arnold/python-block-disposable-email
Author: Max Arnold
Author-email: arnold.maxim@gmail.com
License: BSD
Keywords: block disposable email domains
Platform: any
Classifier: Development Status :: 5 - Production/Stable
Classifier: Intended Audience :: Developers
Classifier: License :: OSI Approved :: BSD License
Classifier: Topic :: Software Development :: Libraries :: Python Modules
Classifier: Topic :: Internet
Classifier: Operating System :: OS Independent
Classifier: Programming Language :: Python
Classifier: Programming Language :: Python :: 3
